CHANGELOG.txt
LICENSE.txt
MANIFEST.in
README.md
setup.py
TkOffice/NewCalc.py
TkOffice/Newfile.py
TkOffice/__init__.py
TkOffice.egg-info/PKG-INFO
TkOffice.egg-info/SOURCES.txt
TkOffice.egg-info/dependency_links.txt
TkOffice.egg-info/requires.txt
TkOffice.egg-info/top_level.txt