Metadata-Version: 2.1
Name: TkOffice
Version: 0.0.5
Summary: A Mordernised version of Tkinter, HighDPI for Windows 10, contains some new functions and widgets, Windows 10 exe development with Windows 10 looks 
Home-page: UNKNOWN
Author: Zin-Lin-Htun
Author-email: zinlinhtun34@gmail.com
License: UNKNOWN
Keywords: tkinter
Platform: UNKNOWN
Classifier: Programming Language :: Python :: 3
Classifier: License :: OSI Approved :: MIT License
Classifier: Operating System :: Microsoft :: Windows :: Windows 10
Requires-Python: >=3.8
